auto_restart
tests
